cmake_presets/__init__.py
cmake_presets/condition.py
cmake_presets/hooks.py
cmake_presets/items.py
cmake_presets/macro.py
cmake_presets/presets.py
cmake_presets/vendor.py
pytest_cmake_presets-0.0.0.dev0.dist-info/entry_points.txt
pytest_cmake_presets-0.0.0.dev0.dist-info/LICENSE.md
pytest_cmake_presets-0.0.0.dev0.dist-info/WHEEL
pytest_cmake_presets-0.0.0.dev0.dist-info/METADATA
pytest_cmake_presets-0.0.0.dev0.dist-info/RECORD
