Metadata-Version: 2.1
Name: pytest-cmake-presets
Version: 0.0.0.dev0
Summary: Execute CMake Presets via pytest
Author: Izzy Muerte
Requires-Python: >=3.10,<4.0
Classifier: Programming Language :: Python :: 3
Classifier: Programming Language :: Python :: 3.10
Requires-Dist: dataclasses-json (>=0.5.7,<0.6.0)
Requires-Dist: pytest (>=7.2.0,<8.0.0)
